yyx_tools/__init__.py
yyx_tools/file.py
yyx_tools/list.py
yyx_tools/utils.py
yyx_tools/video.py
yyx_tools-0.0.16.dist-info/LICENSE
yyx_tools-0.0.16.dist-info/METADATA
yyx_tools-0.0.16.dist-info/WHEEL
yyx_tools-0.0.16.dist-info/top_level.txt
yyx_tools-0.0.16.dist-info/RECORD
