Metadata-Version: 2.1
Name: yyx-tools
Version: 0.0.16
Summary: tools for algorithm engineer
Home-page: https://github.com/yanyuxiangToday/yyx_tools
Author: yanyuxiangtoday
Author-email: yanyuxiangtoday@163.com
License: UNKNOWN
Platform: UNKNOWN
Classifier: Programming Language :: Python :: 3
Classifier: License :: OSI Approved :: MIT License
Classifier: Operating System :: OS Independent
License-File: LICENSE
